texlivemetadata/__init__.py
texlivemetadata/packages.py
texlivemetadata/texlive.py
texlivemetadata-0.1.3.dist-info/LICENSE
texlivemetadata-0.1.3.dist-info/METADATA
texlivemetadata-0.1.3.dist-info/WHEEL
texlivemetadata-0.1.3.dist-info/top_level.txt
texlivemetadata-0.1.3.dist-info/zip-safe
texlivemetadata-0.1.3.dist-info/RECORD
