Metadata-Version: 2.1
Name: texlivemetadata
Version: 0.1.3
Summary: A library for getting information on TexLive installation
Home-page: https://github.com/YtoTech/python-texlivemetadata
Author: Yoan Tournade
Author-email: yoan@ytotech.com
License: MIT
Platform: any
